F:\java\workspace-1\inside-the-jvm\class-structure\target\classes\com\yanghui\learn\clazz>javap -v TestClass.class
Classfile /F:/java/workspace-1/inside-the-jvm/class-structure/target/classes/com/yanghui/learn/clazz/TestClass.class
  Last modified 2020-6-2; size 477 bytes
  MD5 checksum 9b6bc01330218f71f1a8662d0d57fed3
  Compiled from "TestClass.java"
public class com.yanghui.learn.clazz.TestClass
  minor version: 0
  major version: 52
  flags: ACC_PUBLIC, ACC_SUPER
Constant pool:
   #1 = Methodref          #4.#20         // java/lang/Object."<init>":()V
   #2 = Fieldref           #3.#21         // com/yanghui/learn/clazz/TestClass.m:I
   #3 = Class              #22            // com/yanghui/learn/clazz/TestClass
   #4 = Class              #23            // java/lang/Object
   #5 = Utf8               m
   #6 = Utf8               I
   #7 = Utf8               <init>
   #8 = Utf8               ()V
   #9 = Utf8               Code
  #10 = Utf8               LineNumberTable
  #11 = Utf8               LocalVariableTable
  #12 = Utf8               this
  #13 = Utf8               Lcom/yanghui/learn/clazz/TestClass;
  #14 = Utf8               inc
  #15 = Utf8               ()I
  #16 = Utf8               (I)I
  #17 = Utf8               i
  #18 = Utf8               SourceFile
  #19 = Utf8               TestClass.java
  #20 = NameAndType        #7:#8          // "<init>":()V
  #21 = NameAndType        #5:#6          // m:I
  #22 = Utf8               com/yanghui/learn/clazz/TestClass
  #23 = Utf8               java/lang/Object
{
  public com.yanghui.learn.clazz.TestClass();
    descriptor: ()V
    flags: ACC_PUBLIC
    Code:
      stack=1, locals=1, args_size=1
         0: aload_0
         1: invokespecial #1                  // Method java/lang/Object."<init>":()V
         4: return
      LineNumberTable:
        line 7: 0
      LocalVariableTable:
        Start  Length  Slot  Name   Signature
            0       5     0  this   Lcom/yanghui/learn/clazz/TestClass;

  public strictfp int inc();
    descriptor: ()I
    flags: ACC_PUBLIC, ACC_STRICT
    Code:
      stack=2, locals=1, args_size=1
         0: aload_0
         1: getfield      #2                  // Field m:I
         4: iconst_1
         5: iadd
         6: ireturn
      LineNumberTable:
        line 12: 0
      LocalVariableTable:
        Start  Length  Slot  Name   Signature
            0       7     0  this   Lcom/yanghui/learn/clazz/TestClass;

  public static int inc(int);
    descriptor: (I)I
    flags: ACC_PUBLIC, ACC_STATIC
    Code:
      stack=1, locals=1, args_size=1
         0: iinc          0, 1
         3: iload_0
         4: ireturn
      LineNumberTable:
        line 16: 0
        line 17: 3
      LocalVariableTable:
        Start  Length  Slot  Name   Signature
            0       5     0     i   I
}
SourceFile: "TestClass.java"