D:\workspace-2\inside-the-jvm\class-structure\target\classes\com\yanghui\learn\clazz>javap -v TestClass4.class
Classfile /D:/workspace-2/inside-the-jvm/class-structure/target/classes/com/yanghui/learn/clazz/TestClass4.class
  Last modified 2020-5-21; size 1005 bytes
  MD5 checksum b33caae9fb24c1aa3b18da8423ccaadb
  Compiled from "TestClass4.java"
public class com.yanghui.learn.clazz.TestClass4<T extends java.lang.Object> extends java.lang.Object implements java.io.Serializable
  minor version: 0
  major version: 52
  flags: ACC_PUBLIC, ACC_SUPER
Constant pool:
   #1 = Methodref          #7.#36         // java/lang/Object."<init>":()V
   #2 = Fieldref           #6.#37         // com/yanghui/learn/clazz/TestClass4.n:I
   #3 = Fieldref           #6.#38         // com/yanghui/learn/clazz/TestClass4.m:I
   #4 = String             #39            // B
   #5 = Fieldref           #6.#40         // com/yanghui/learn/clazz/TestClass4.b:Ljava/lang/String;
   #6 = Class              #41            // com/yanghui/learn/clazz/TestClass4
   #7 = Class              #42            // java/lang/Object
   #8 = Class              #43            // java/io/Serializable
   #9 = Utf8               m
  #10 = Utf8               I
  #11 = Utf8               n
  #12 = Utf8               b
  #13 = Utf8               Ljava/lang/String;
  #14 = Utf8               t
  #15 = Utf8               Ljava/lang/Object;
  #16 = Utf8               Signature
  #17 = Utf8               TT;
  #18 = Utf8               <init>
  #19 = Utf8               ()V
  #20 = Utf8               Code
  #21 = Utf8               LineNumberTable
  #22 = Utf8               LocalVariableTable
  #23 = Utf8               this
  #24 = Utf8               Lcom/yanghui/learn/clazz/TestClass4;
  #25 = Utf8               LocalVariableTypeTable
  #26 = Utf8               Lcom/yanghui/learn/clazz/TestClass4<TT;>;
  #27 = Utf8               inc
  #28 = Utf8               ()I
  #29 = Utf8               (I)I
  #30 = Utf8               i
  #31 = Utf8               dec
  #32 = Utf8               <clinit>
  #33 = Utf8               <T:Ljava/lang/Object;>Ljava/lang/Object;Ljava/io/Serializable;
  #34 = Utf8               SourceFile
  #35 = Utf8               TestClass4.java
  #36 = NameAndType        #18:#19        // "<init>":()V
  #37 = NameAndType        #11:#10        // n:I
  #38 = NameAndType        #9:#10         // m:I
  #39 = Utf8               B
  #40 = NameAndType        #12:#13        // b:Ljava/lang/String;
  #41 = Utf8               com/yanghui/learn/clazz/TestClass4
  #42 = Utf8               java/lang/Object
  #43 = Utf8               java/io/Serializable
{
  static java.lang.String b;
    descriptor: Ljava/lang/String;
    flags: ACC_STATIC

  public com.yanghui.learn.clazz.TestClass4();
    descriptor: ()V
    flags: ACC_PUBLIC
    Code:
      stack=2, locals=1, args_size=1
         0: aload_0
         1: invokespecial #1                  // Method java/lang/Object."<init>":()V
         4: aload_0
         5: bipush        66
         7: putfield      #2                  // Field n:I
        10: return
      LineNumberTable:
        line 12: 0
        line 16: 4
      LocalVariableTable:
        Start  Length  Slot  Name   Signature
            0      11     0  this   Lcom/yanghui/learn/clazz/TestClass4;
      LocalVariableTypeTable:
        Start  Length  Slot  Name   Signature
            0      11     0  this   Lcom/yanghui/learn/clazz/TestClass4<TT;>;

  public final int inc();
    descriptor: ()I
    flags: ACC_PUBLIC, ACC_FINAL
    Code:
      stack=2, locals=1, args_size=1
         0: aload_0
         1: getfield      #3                  // Field m:I
         4: iconst_1
         5: iadd
         6: ireturn
      LineNumberTable:
        line 23: 0
      LocalVariableTable:
        Start  Length  Slot  Name   Signature
            0       7     0  this   Lcom/yanghui/learn/clazz/TestClass4;
      LocalVariableTypeTable:
        Start  Length  Slot  Name   Signature
            0       7     0  this   Lcom/yanghui/learn/clazz/TestClass4<TT;>;

  public int inc(int);
    descriptor: (I)I
    flags: ACC_PUBLIC
    Code:
      stack=2, locals=2, args_size=2
         0: aload_0
         1: getfield      #3                  // Field m:I
         4: iload_1
         5: iadd
         6: ireturn
      LineNumberTable:
        line 27: 0
      LocalVariableTable:
        Start  Length  Slot  Name   Signature
            0       7     0  this   Lcom/yanghui/learn/clazz/TestClass4;
            0       7     1     i   I
      LocalVariableTypeTable:
        Start  Length  Slot  Name   Signature
            0       7     0  this   Lcom/yanghui/learn/clazz/TestClass4<TT;>;

  public int dec(int);
    descriptor: (I)I
    flags: ACC_PUBLIC
    Code:
      stack=2, locals=2, args_size=2
         0: aload_0
         1: getfield      #3                  // Field m:I
         4: iload_1
         5: isub
         6: ireturn
      LineNumberTable:
        line 31: 0
      LocalVariableTable:
        Start  Length  Slot  Name   Signature
            0       7     0  this   Lcom/yanghui/learn/clazz/TestClass4;
            0       7     1     i   I
      LocalVariableTypeTable:
        Start  Length  Slot  Name   Signature
            0       7     0  this   Lcom/yanghui/learn/clazz/TestClass4<TT;>;

  static {};
    descriptor: ()V
    flags: ACC_STATIC
    Code:
      stack=1, locals=0, args_size=0
         0: ldc           #4                  // String B
         2: putstatic     #5                  // Field b:Ljava/lang/String;
         5: return
      LineNumberTable:
        line 18: 0
}
Signature: #33                          // <T:Ljava/lang/Object;>Ljava/lang/Object;Ljava/io/Serializable;
SourceFile: "TestClass4.java"
